Metadata-Version: 2.1
Name: django-celery-beat-kozlek
Version: 2.5.0
Summary: Database-backed Periodic Tasks.
Home-page: https://github.com/celery/django-celery-beat
Author: Asif Saif Uddin, Ask Solem
Author-email: auvipy@gmail.com, ask@celeryproject.org
License: BSD
Keywords: django celery beat periodic task database
Platform: any
Classifier: Development Status :: 5 - Production/Stable
Classifier: License :: OSI Approved :: BSD License
Classifier: Programming Language :: Python
Classifier: Programming Language :: Python :: 3
Classifier: Programming Language :: Python :: 3.8
Classifier: Programming Language :: Python :: 3.9
Classifier: Programming Language :: Python :: 3.10
Classifier: Programming Language :: Python :: 3.11
Classifier: Programming Language :: Python :: 3.12
Classifier: Programming Language :: Python :: Implementation :: CPython
Classifier: Programming Language :: Python :: Implementation :: PyPy
Classifier: Framework :: Django
Classifier: Framework :: Django :: 3.2
Classifier: Framework :: Django :: 4.1
Classifier: Framework :: Django :: 4.2
Classifier: Operating System :: OS Independent
Classifier: Topic :: Communications
Classifier: Topic :: System :: Distributed Computing
Classifier: Topic :: Software Development :: Libraries :: Python Modules
License-File: LICENSE
License-File: AUTHORS
Requires-Dist: celery <6.0,>=5.2.3
Requires-Dist: django-timezone-field >=5.0
Requires-Dist: tzdata
Requires-Dist: python-crontab >=2.3.4
Requires-Dist: cron-descriptor >=1.2.32
Requires-Dist: Django <5.1,>=2.2
Requires-Dist: importlib-metadata <5.0 ; python_version < "3.8"
Requires-Dist: backports.zoneinfo ; python_version < "3.9"
